{"box_data": [{"position": {"minX": 421.5, "minY": 176.75, "maxX": 451.5, "maxY": 203.5}, "class_id": 3, "box_caption": "other 0.571", "scores": {"class_score": 0.5712890625}, "domain": "pixel"}, {"position": {"minX": 218.75, "minY": 254.875, "maxX": 232.75, "maxY": 268.25}, "class_id": 3, "box_caption": "other 0.246", "scores": {"class_score": 0.24560546875}, "domain": "pixel"}, {"position": {"minX": 218.75, "minY": 254.875, "maxX": 232.75, "maxY": 268.25}, "class_id": 2, "box_caption": "mandatory 0.122", "scores": {"class_score": 0.1219482421875}, "domain": "pixel"}, {"position": {"minX": 421.5, "minY": 176.75, "maxX": 451.5, "maxY": 203.5}, "class_id": 2, "box_caption": "mandatory 0.114", "scores": {"class_score": 0.114013671875}, "domain": "pixel"}, {"position": {"minX": 327.0, "minY": 260.5, "maxX": 339.5, "maxY": 271.5}, "class_id": 1, "box_caption": "danger 0.047", "scores": {"class_score": 0.046905517578125}, "domain": "pixel"}, {"position": {"minX": 413.5, "minY": 172.25, "maxX": 450.5, "maxY": 200.25}, "class_id": 3, "box_caption": "other 0.043", "scores": {"class_score": 0.043365478515625}, "domain": "pixel"}, {"position": {"minX": 218.75, "minY": 254.875, "maxX": 232.75, "maxY": 268.25}, "class_id": 0, "box_caption": "prohibitory 0.042", "scores": {"class_score": 0.041778564453125}, "domain": "pixel"}, {"position": {"minX": 414.5, "minY": 178.375, "maxX": 456.5, "maxY": 207.625}, "class_id": 3, "box_caption": "other 0.039", "scores": {"class_score": 0.039031982421875}, "domain": "pixel"}, {"position": {"minX": 420.5, "minY": 174.875, "maxX": 451.5, "maxY": 205.875}, "class_id": 1, "box_caption": "danger 0.034", "scores": {"class_score": 0.033721923828125}, "domain": "pixel"}, {"position": {"minX": 221.375, "minY": 253.25, "maxX": 234.375, "maxY": 265.75}, "class_id": 3, "box_caption": "other 0.032", "scores": {"class_score": 0.03240966796875}, "domain": "pixel"}, {"position": {"minX": 195.0, "minY": 205.0, "maxX": 210.5, "maxY": 225.25}, "class_id": 1, "box_caption": "danger 0.027", "scores": {"class_score": 0.027069091796875}, "domain": "pixel"}, {"position": {"minX": 218.75, "minY": 254.875, "maxX": 232.75, "maxY": 268.25}, "class_id": 1, "box_caption": "danger 0.027", "scores": {"class_score": 0.0267486572265625}, "domain": "pixel"}, {"position": {"minX": 327.5, "minY": 262.0, "maxX": 338.5, "maxY": 272.0}, "class_id": 2, "box_caption": "mandatory 0.022", "scores": {"class_score": 0.02227783203125}, "domain": "pixel"}, {"position": {"minX": 328.0, "minY": 261.5, "maxX": 338.0, "maxY": 272.5}, "class_id": 3, "box_caption": "other 0.016", "scores": {"class_score": 0.0164031982421875}, "domain": "pixel"}, {"position": {"minX": 327.5, "minY": 262.0, "maxX": 338.5, "maxY": 272.0}, "class_id": 0, "box_caption": "prohibitory 0.014", "scores": {"class_score": 0.01419830322265625}, "domain": "pixel"}, {"position": {"minX": 225.25, "minY": 257.0, "maxX": 238.25, "maxY": 270.5}, "class_id": 3, "box_caption": "other 0.014", "scores": {"class_score": 0.013885498046875}, "domain": "pixel"}, {"position": {"minX": 221.375, "minY": 253.25, "maxX": 234.375, "maxY": 265.75}, "class_id": 2, "box_caption": "mandatory 0.013", "scores": {"class_score": 0.0129547119140625}, "domain": "pixel"}, {"position": {"minX": 195.5, "minY": 212.125, "maxX": 208.0, "maxY": 228.125}, "class_id": 1, "box_caption": "danger 0.013", "scores": {"class_score": 0.0129241943359375}, "domain": "pixel"}, {"position": {"minX": 409.75, "minY": 160.625, "maxX": 461.25, "maxY": 210.375}, "class_id": 3, "box_caption": "other 0.013", "scores": {"class_score": 0.01284027099609375}, "domain": "pixel"}, {"position": {"minX": 327.5, "minY": 259.75, "maxX": 342.5, "maxY": 273.25}, "class_id": 3, "box_caption": "other 0.013", "scores": {"class_score": 0.0125274658203125}, "domain": "pixel"}, {"position": {"minX": 404.75, "minY": 177.625, "maxX": 444.25, "maxY": 205.125}, "class_id": 3, "box_caption": "other 0.012", "scores": {"class_score": 0.012237548828125}, "domain": "pixel"}, {"position": {"minX": 326.5, "minY": 258.75, "maxX": 342.5, "maxY": 275.25}, "class_id": 1, "box_caption": "danger 0.011", "scores": {"class_score": 0.01120758056640625}, "domain": "pixel"}, {"position": {"minX": 220.625, "minY": 259.0, "maxX": 231.875, "maxY": 272.0}, "class_id": 3, "box_caption": "other 0.011", "scores": {"class_score": 0.01097869873046875}, "domain": "pixel"}, {"position": {"minX": 421.5, "minY": 176.75, "maxX": 451.5, "maxY": 203.5}, "class_id": 0, "box_caption": "prohibitory 0.011", "scores": {"class_score": 0.01061248779296875}, "domain": "pixel"}, {"position": {"minX": 220.625, "minY": 259.0, "maxX": 231.875, "maxY": 272.0}, "class_id": 2, "box_caption": "mandatory 0.010", "scores": {"class_score": 0.01042938232421875}, "domain": "pixel"}, {"position": {"minX": 146.125, "minY": 294.5, "maxX": 161.125, "maxY": 305.5}, "class_id": 3, "box_caption": "other 0.009", "scores": {"class_score": 0.00904083251953125}, "domain": "pixel"}, {"position": {"minX": 195.0, "minY": 205.0, "maxX": 210.5, "maxY": 225.25}, "class_id": 3, "box_caption": "other 0.009", "scores": {"class_score": 0.00876617431640625}, "domain": "pixel"}, {"position": {"minX": 413.5, "minY": 172.25, "maxX": 450.5, "maxY": 200.25}, "class_id": 2, "box_caption": "mandatory 0.008", "scores": {"class_score": 0.00775146484375}, "domain": "pixel"}, {"position": {"minX": 192.0, "minY": 199.875, "maxX": 209.75, "maxY": 218.125}, "class_id": 1, "box_caption": "danger 0.008", "scores": {"class_score": 0.00762176513671875}, "domain": "pixel"}, {"position": {"minX": 225.25, "minY": 257.0, "maxX": 238.25, "maxY": 270.5}, "class_id": 2, "box_caption": "mandatory 0.007", "scores": {"class_score": 0.006801605224609375}, "domain": "pixel"}, {"position": {"minX": 194.5, "minY": 209.75, "maxX": 208.75, "maxY": 228.0}, "class_id": 3, "box_caption": "other 0.006", "scores": {"class_score": 0.0064544677734375}, "domain": "pixel"}, {"position": {"minX": 221.375, "minY": 253.25, "maxX": 234.375, "maxY": 265.75}, "class_id": 0, "box_caption": "prohibitory 0.006", "scores": {"class_score": 0.006031036376953125}, "domain": "pixel"}, {"position": {"minX": 228.875, "minY": 261.5, "maxX": 240.375, "maxY": 274.5}, "class_id": 3, "box_caption": "other 0.006", "scores": {"class_score": 0.005931854248046875}, "domain": "pixel"}, {"position": {"minX": 195.5, "minY": 212.125, "maxX": 208.0, "maxY": 228.125}, "class_id": 2, "box_caption": "mandatory 0.006", "scores": {"class_score": 0.005687713623046875}, "domain": "pixel"}, {"position": {"minX": 220.625, "minY": 259.0, "maxX": 231.875, "maxY": 272.0}, "class_id": 0, "box_caption": "prohibitory 0.005", "scores": {"class_score": 0.00537872314453125}, "domain": "pixel"}, {"position": {"minX": 414.5, "minY": 178.375, "maxX": 456.5, "maxY": 207.625}, "class_id": 2, "box_caption": "mandatory 0.005", "scores": {"class_score": 0.00522613525390625}, "domain": "pixel"}, {"position": {"minX": 221.375, "minY": 253.25, "maxX": 234.375, "maxY": 265.75}, "class_id": 1, "box_caption": "danger 0.005", "scores": {"class_score": 0.005100250244140625}, "domain": "pixel"}, {"position": {"minX": 194.875, "minY": 207.125, "maxX": 210.875, "maxY": 223.875}, "class_id": 2, "box_caption": "mandatory 0.005", "scores": {"class_score": 0.004901885986328125}, "domain": "pixel"}, {"position": {"minX": 398.5, "minY": 185.0, "maxX": 430.5, "maxY": 208.75}, "class_id": 3, "box_caption": "other 0.005", "scores": {"class_score": 0.004825592041015625}, "domain": "pixel"}, {"position": {"minX": 196.125, "minY": 208.75, "maxX": 209.125, "maxY": 221.0}, "class_id": 1, "box_caption": "danger 0.005", "scores": {"class_score": 0.0047760009765625}, "domain": "pixel"}, {"position": {"minX": 254.625, "minY": 7.375, "maxX": 616.0, "maxY": 341.0}, "class_id": 2, "box_caption": "mandatory 0.005", "scores": {"class_score": 0.004741668701171875}, "domain": "pixel"}, {"position": {"minX": 233.25, "minY": 47.625, "maxX": 637.0, "maxY": 370.5}, "class_id": 0, "box_caption": "prohibitory 0.005", "scores": {"class_score": 0.00463104248046875}, "domain": "pixel"}, {"position": {"minX": 224.5, "minY": 264.75, "maxX": 234.0, "maxY": 275.75}, "class_id": 0, "box_caption": "prohibitory 0.005", "scores": {"class_score": 0.0045623779296875}, "domain": "pixel"}, {"position": {"minX": 327.5, "minY": 259.75, "maxX": 342.5, "maxY": 273.25}, "class_id": 2, "box_caption": "mandatory 0.004", "scores": {"class_score": 0.004497528076171875}, "domain": "pixel"}, {"position": {"minX": 195.5, "minY": 204.0, "maxX": 208.75, "maxY": 219.0}, "class_id": 1, "box_caption": "danger 0.004", "scores": {"class_score": 0.004482269287109375}, "domain": "pixel"}, {"position": {"minX": 222.625, "minY": 257.75, "maxX": 238.625, "maxY": 275.75}, "class_id": 3, "box_caption": "other 0.004", "scores": {"class_score": 0.0044708251953125}, "domain": "pixel"}, {"position": {"minX": 220.625, "minY": 259.0, "maxX": 231.875, "maxY": 272.0}, "class_id": 1, "box_caption": "danger 0.004", "scores": {"class_score": 0.00446319580078125}, "domain": "pixel"}, {"position": {"minX": 254.625, "minY": 7.375, "maxX": 616.0, "maxY": 341.0}, "class_id": 3, "box_caption": "other 0.004", "scores": {"class_score": 0.0043487548828125}, "domain": "pixel"}, {"position": {"minX": 187.125, "minY": 141.125, "maxX": 224.125, "maxY": 168.375}, "class_id": 3, "box_caption": "other 0.004", "scores": {"class_score": 0.00418853759765625}, "domain": "pixel"}, {"position": {"minX": 147.125, "minY": 294.5, "maxX": 160.625, "maxY": 306.0}, "class_id": 2, "box_caption": "mandatory 0.004", "scores": {"class_score": 0.004077911376953125}, "domain": "pixel"}, {"position": {"minX": 254.625, "minY": 7.375, "maxX": 616.0, "maxY": 341.0}, "class_id": 1, "box_caption": "danger 0.004", "scores": {"class_score": 0.003963470458984375}, "domain": "pixel"}, {"position": {"minX": 325.75, "minY": 262.25, "maxX": 336.75, "maxY": 273.25}, "class_id": 1, "box_caption": "danger 0.004", "scores": {"class_score": 0.0038509368896484375}, "domain": "pixel"}, {"position": {"minX": 224.5, "minY": 264.75, "maxX": 234.0, "maxY": 275.75}, "class_id": 2, "box_caption": "mandatory 0.004", "scores": {"class_score": 0.003627777099609375}, "domain": "pixel"}, {"position": {"minX": 405.0, "minY": 163.5, "maxX": 468.0, "maxY": 215.5}, "class_id": 0, "box_caption": "prohibitory 0.003", "scores": {"class_score": 0.0034732818603515625}, "domain": "pixel"}, {"position": {"minX": 195.125, "minY": 210.75, "maxX": 207.375, "maxY": 226.75}, "class_id": 0, "box_caption": "prohibitory 0.003", "scores": {"class_score": 0.00345611572265625}, "domain": "pixel"}, {"position": {"minX": 228.875, "minY": 261.5, "maxX": 240.375, "maxY": 274.5}, "class_id": 2, "box_caption": "mandatory 0.003", "scores": {"class_score": 0.003307342529296875}, "domain": "pixel"}, {"position": {"minX": 190.25, "minY": 215.75, "maxX": 217.5, "maxY": 239.25}, "class_id": 1, "box_caption": "danger 0.003", "scores": {"class_score": 0.0032901763916015625}, "domain": "pixel"}, {"position": {"minX": 191.875, "minY": 197.625, "maxX": 208.625, "maxY": 219.125}, "class_id": 3, "box_caption": "other 0.003", "scores": {"class_score": 0.0032501220703125}, "domain": "pixel"}, {"position": {"minX": 409.0, "minY": 144.375, "maxX": 443.5, "maxY": 170.625}, "class_id": 3, "box_caption": "other 0.003", "scores": {"class_score": 0.003231048583984375}, "domain": "pixel"}, {"position": {"minX": 185.375, "minY": 199.5, "maxX": 215.875, "maxY": 228.75}, "class_id": 1, "box_caption": "danger 0.003", "scores": {"class_score": 0.003185272216796875}, "domain": "pixel"}, {"position": {"minX": 146.375, "minY": 291.0, "maxX": 163.625, "maxY": 308.5}, "class_id": 3, "box_caption": "other 0.003", "scores": {"class_score": 0.0030612945556640625}, "domain": "pixel"}, {"position": {"minX": 325.25, "minY": 262.25, "maxX": 336.25, "maxY": 272.75}, "class_id": 3, "box_caption": "other 0.003", "scores": {"class_score": 0.0030517578125}, "domain": "pixel"}, {"position": {"minX": 211.75, "minY": 251.75, "maxX": 241.0, "maxY": 277.75}, "class_id": 1, "box_caption": "danger 0.003", "scores": {"class_score": 0.0030231475830078125}, "domain": "pixel"}, {"position": {"minX": 409.75, "minY": 160.625, "maxX": 461.25, "maxY": 210.375}, "class_id": 2, "box_caption": "mandatory 0.003", "scores": {"class_score": 0.0029888153076171875}, "domain": "pixel"}, {"position": {"minX": 409.75, "minY": 160.625, "maxX": 461.25, "maxY": 210.375}, "class_id": 1, "box_caption": "danger 0.003", "scores": {"class_score": 0.002986907958984375}, "domain": "pixel"}, {"position": {"minX": 47.53125, "minY": 248.0, "maxX": 60.84375, "maxY": 262.5}, "class_id": 3, "box_caption": "other 0.003", "scores": {"class_score": 0.0029430389404296875}, "domain": "pixel"}, {"position": {"minX": 195.375, "minY": 198.5, "maxX": 207.375, "maxY": 216.25}, "class_id": 1, "box_caption": "danger 0.003", "scores": {"class_score": 0.0029048919677734375}, "domain": "pixel"}, {"position": {"minX": 347.5, "minY": 202.25, "maxX": 379.5, "maxY": 225.75}, "class_id": 3, "box_caption": "other 0.003", "scores": {"class_score": 0.0028514862060546875}, "domain": "pixel"}, {"position": {"minX": 327.5, "minY": 259.75, "maxX": 342.5, "maxY": 273.25}, "class_id": 0, "box_caption": "prohibitory 0.003", "scores": {"class_score": 0.0028514862060546875}, "domain": "pixel"}, {"position": {"minX": 222.625, "minY": 257.75, "maxX": 238.625, "maxY": 275.75}, "class_id": 1, "box_caption": "danger 0.003", "scores": {"class_score": 0.0028438568115234375}, "domain": "pixel"}, {"position": {"minX": 224.5, "minY": 264.75, "maxX": 234.0, "maxY": 275.75}, "class_id": 3, "box_caption": "other 0.003", "scores": {"class_score": 0.0027637481689453125}, "domain": "pixel"}, {"position": {"minX": 225.25, "minY": 257.0, "maxX": 238.25, "maxY": 270.5}, "class_id": 0, "box_caption": "prohibitory 0.003", "scores": {"class_score": 0.002643585205078125}, "domain": "pixel"}, {"position": {"minX": 186.0, "minY": 151.25, "maxX": 218.0, "maxY": 176.25}, "class_id": 3, "box_caption": "other 0.003", "scores": {"class_score": 0.0025348663330078125}, "domain": "pixel"}, {"position": {"minX": 273.25, "minY": 228.75, "maxX": 285.25, "maxY": 241.25}, "class_id": 3, "box_caption": "other 0.002", "scores": {"class_score": 0.002361297607421875}, "domain": "pixel"}, {"position": {"minX": 253.875, "minY": 239.0, "maxX": 266.0, "maxY": 251.5}, "class_id": 3, "box_caption": "other 0.002", "scores": {"class_score": 0.002227783203125}, "domain": "pixel"}, {"position": {"minX": 404.75, "minY": 94.625, "maxX": 437.25, "maxY": 119.375}, "class_id": 3, "box_caption": "other 0.002", "scores": {"class_score": 0.002132415771484375}, "domain": "pixel"}, {"position": {"minX": 194.875, "minY": 207.125, "maxX": 210.875, "maxY": 223.875}, "class_id": 0, "box_caption": "prohibitory 0.002", "scores": {"class_score": 0.0021266937255859375}, "domain": "pixel"}, {"position": {"minX": 414.5, "minY": 178.375, "maxX": 456.5, "maxY": 207.625}, "class_id": 0, "box_caption": "prohibitory 0.002", "scores": {"class_score": 0.0021228790283203125}, "domain": "pixel"}, {"position": {"minX": 390.0, "minY": 93.5, "maxX": 425.5, "maxY": 120.625}, "class_id": 3, "box_caption": "other 0.002", "scores": {"class_score": 0.0021114349365234375}, "domain": "pixel"}, {"position": {"minX": 215.875, "minY": 241.0, "maxX": 242.625, "maxY": 279.5}, "class_id": 3, "box_caption": "other 0.002", "scores": {"class_score": 0.002044677734375}, "domain": "pixel"}, {"position": {"minX": 214.0, "minY": 168.0, "maxX": 247.25, "maxY": 192.0}, "class_id": 3, "box_caption": "other 0.002", "scores": {"class_score": 0.0019893646240234375}, "domain": "pixel"}, {"position": {"minX": 534.5, "minY": 297.75, "maxX": 553.5, "maxY": 312.75}, "class_id": 1, "box_caption": "danger 0.002", "scores": {"class_score": 0.00191497802734375}, "domain": "pixel"}, {"position": {"minX": 145.375, "minY": 290.0, "maxX": 162.625, "maxY": 307.0}, "class_id": 1, "box_caption": "danger 0.002", "scores": {"class_score": 0.0019006729125976562}, "domain": "pixel"}, {"position": {"minX": 205.25, "minY": 252.375, "maxX": 234.75, "maxY": 274.75}, "class_id": 1, "box_caption": "danger 0.002", "scores": {"class_score": 0.0018968582153320312}, "domain": "pixel"}, {"position": {"minX": 209.125, "minY": 248.0, "maxX": 237.625, "maxY": 280.0}, "class_id": 3, "box_caption": "other 0.002", "scores": {"class_score": 0.0018720626831054688}, "domain": "pixel"}, {"position": {"minX": 252.875, "minY": 169.625, "maxX": 289.0, "maxY": 196.375}, "class_id": 3, "box_caption": "other 0.002", "scores": {"class_score": 0.0018606185913085938}, "domain": "pixel"}, {"position": {"minX": 176.25, "minY": 128.625, "maxX": 242.5, "maxY": 174.125}, "class_id": 3, "box_caption": "other 0.002", "scores": {"class_score": 0.001766204833984375}, "domain": "pixel"}, {"position": {"minX": 226.625, "minY": 257.25, "maxX": 237.125, "maxY": 270.75}, "class_id": 1, "box_caption": "danger 0.002", "scores": {"class_score": 0.0017642974853515625}, "domain": "pixel"}, {"position": {"minX": 413.5, "minY": 172.25, "maxX": 450.5, "maxY": 200.25}, "class_id": 0, "box_caption": "prohibitory 0.002", "scores": {"class_score": 0.001758575439453125}, "domain": "pixel"}, {"position": {"minX": 222.625, "minY": 257.75, "maxX": 238.625, "maxY": 275.75}, "class_id": 2, "box_caption": "mandatory 0.002", "scores": {"class_score": 0.0017099380493164062}, "domain": "pixel"}, {"position": {"minX": 603.0, "minY": 30.40625, "maxX": 647.0, "maxY": 66.0}, "class_id": 3, "box_caption": "other 0.002", "scores": {"class_score": 0.0017004013061523438}, "domain": "pixel"}, {"position": {"minX": 233.375, "minY": 257.75, "maxX": 247.125, "maxY": 275.75}, "class_id": 3, "box_caption": "other 0.002", "scores": {"class_score": 0.001697540283203125}, "domain": "pixel"}, {"position": {"minX": 604.5, "minY": 9.2734375, "maxX": 645.5, "maxY": 39.96875}, "class_id": 3, "box_caption": "other 0.002", "scores": {"class_score": 0.0016937255859375}, "domain": "pixel"}, {"position": {"minX": 214.375, "minY": 242.125, "maxX": 244.375, "maxY": 268.75}, "class_id": 1, "box_caption": "danger 0.002", "scores": {"class_score": 0.0016880035400390625}, "domain": "pixel"}, {"position": {"minX": 279.75, "minY": 198.25, "maxX": 310.75, "maxY": 222.0}, "class_id": 3, "box_caption": "other 0.002", "scores": {"class_score": 0.0016775131225585938}, "domain": "pixel"}, {"position": {"minX": 314.25, "minY": 241.875, "maxX": 346.25, "maxY": 267.0}, "class_id": 3, "box_caption": "other 0.002", "scores": {"class_score": 0.0016584396362304688}, "domain": "pixel"}, {"position": {"minX": 146.125, "minY": 294.5, "maxX": 161.125, "maxY": 305.5}, "class_id": 0, "box_caption": "prohibitory 0.002", "scores": {"class_score": 0.00164794921875}, "domain": "pixel"}, {"position": {"minX": 417.25, "minY": 173.0, "maxX": 440.25, "maxY": 197.5}, "class_id": 3, "box_caption": "other 0.002", "scores": {"class_score": 0.0016050338745117188}, "domain": "pixel"}, {"position": {"minX": 385.0, "minY": 173.0, "maxX": 446.0, "maxY": 216.25}, "class_id": 3, "box_caption": "other 0.002", "scores": {"class_score": 0.0015506744384765625}, "domain": "pixel"}, {"position": {"minX": 147.125, "minY": 294.5, "maxX": 160.625, "maxY": 306.0}, "class_id": 1, "box_caption": "danger 0.002", "scores": {"class_score": 0.0015087127685546875}, "domain": "pixel"}, {"position": {"minX": 250.625, "minY": 201.25, "maxX": 282.25, "maxY": 225.25}, "class_id": 3, "box_caption": "other 0.001", "scores": {"class_score": 0.0014982223510742188}, "domain": "pixel"}, {"position": {"minX": 278.5, "minY": 170.375, "maxX": 316.0, "maxY": 198.625}, "class_id": 3, "box_caption": "other 0.001", "scores": {"class_score": 0.0014791488647460938}, "domain": "pixel"}, {"position": {"minX": 317.5, "minY": 200.375, "maxX": 350.5, "maxY": 225.125}, "class_id": 3, "box_caption": "other 0.001", "scores": {"class_score": 0.00147247314453125}, "domain": "pixel"}, {"position": {"minX": 388.25, "minY": 135.125, "maxX": 422.75, "maxY": 160.125}, "class_id": 3, "box_caption": "other 0.001", "scores": {"class_score": 0.0014667510986328125}, "domain": "pixel"}, {"position": {"minX": 404.75, "minY": 177.625, "maxX": 444.25, "maxY": 205.125}, "class_id": 2, "box_caption": "mandatory 0.001", "scores": {"class_score": 0.001461029052734375}, "domain": "pixel"}, {"position": {"minX": 208.75, "minY": 138.125, "maxX": 248.25, "maxY": 168.875}, "class_id": 3, "box_caption": "other 0.001", "scores": {"class_score": 0.0014438629150390625}, "domain": "pixel"}, {"position": {"minX": 346.5, "minY": 222.75, "maxX": 375.0, "maxY": 244.5}, "class_id": 3, "box_caption": "other 0.001", "scores": {"class_score": 0.0014095306396484375}, "domain": "pixel"}, {"position": {"minX": 444.0, "minY": 247.875, "maxX": 455.0, "maxY": 259.25}, "class_id": 3, "box_caption": "other 0.001", "scores": {"class_score": 0.0013456344604492188}, "domain": "pixel"}, {"position": {"minX": 46.625, "minY": 247.375, "maxX": 60.5, "maxY": 261.5}, "class_id": 2, "box_caption": "mandatory 0.001", "scores": {"class_score": 0.0013275146484375}, "domain": "pixel"}, {"position": {"minX": 316.25, "minY": 252.75, "maxX": 346.25, "maxY": 277.25}, "class_id": 1, "box_caption": "danger 0.001", "scores": {"class_score": 0.0013256072998046875}, "domain": "pixel"}, {"position": {"minX": 415.0, "minY": 168.0, "maxX": 431.5, "maxY": 184.5}, "class_id": 3, "box_caption": "other 0.001", "scores": {"class_score": 0.0013208389282226562}, "domain": "pixel"}, {"position": {"minX": 611.0, "minY": 269.25, "maxX": 648.0, "maxY": 297.25}, "class_id": 3, "box_caption": "other 0.001", "scores": {"class_score": 0.00131988525390625}, "domain": "pixel"}, {"position": {"minX": 254.75, "minY": 238.25, "maxX": 266.75, "maxY": 252.0}, "class_id": 2, "box_caption": "mandatory 0.001", "scores": {"class_score": 0.0013103485107421875}, "domain": "pixel"}, {"position": {"minX": 533.5, "minY": 292.5, "maxX": 552.5, "maxY": 312.5}, "class_id": 3, "box_caption": "other 0.001", "scores": {"class_score": 0.0013093948364257812}, "domain": "pixel"}, {"position": {"minX": 427.0, "minY": 187.875, "maxX": 448.5, "maxY": 211.625}, "class_id": 3, "box_caption": "other 0.001", "scores": {"class_score": 0.0013074874877929688}, "domain": "pixel"}, {"position": {"minX": 400.25, "minY": 131.0, "maxX": 459.75, "maxY": 176.75}, "class_id": 3, "box_caption": "other 0.001", "scores": {"class_score": 0.0012683868408203125}, "domain": "pixel"}, {"position": {"minX": 217.375, "minY": 202.875, "maxX": 248.625, "maxY": 227.125}, "class_id": 3, "box_caption": "other 0.001", "scores": {"class_score": 0.0012426376342773438}, "domain": "pixel"}, {"position": {"minX": 182.0, "minY": 105.5625, "maxX": 222.0, "maxY": 135.875}, "class_id": 3, "box_caption": "other 0.001", "scores": {"class_score": 0.0012159347534179688}, "domain": "pixel"}, {"position": {"minX": 228.875, "minY": 261.5, "maxX": 240.375, "maxY": 274.5}, "class_id": 0, "box_caption": "prohibitory 0.001", "scores": {"class_score": 0.0012063980102539062}, "domain": "pixel"}, {"position": {"minX": 233.375, "minY": 257.75, "maxX": 247.125, "maxY": 275.75}, "class_id": 2, "box_caption": "mandatory 0.001", "scores": {"class_score": 0.0011968612670898438}, "domain": "pixel"}, {"position": {"minX": 349.5, "minY": 168.375, "maxX": 386.5, "maxY": 195.875}, "class_id": 3, "box_caption": "other 0.001", "scores": {"class_score": 0.0011816024780273438}, "domain": "pixel"}, {"position": {"minX": 185.375, "minY": 199.5, "maxX": 215.875, "maxY": 228.75}, "class_id": 3, "box_caption": "other 0.001", "scores": {"class_score": 0.0011768341064453125}, "domain": "pixel"}, {"position": {"minX": 408.25, "minY": 174.125, "maxX": 434.75, "maxY": 196.875}, "class_id": 3, "box_caption": "other 0.001", "scores": {"class_score": 0.001171112060546875}, "domain": "pixel"}, {"position": {"minX": 336.0, "minY": 189.75, "maxX": 401.5, "maxY": 231.75}, "class_id": 3, "box_caption": "other 0.001", "scores": {"class_score": 0.0011529922485351562}, "domain": "pixel"}, {"position": {"minX": 405.5, "minY": 73.625, "maxX": 447.0, "maxY": 105.5}, "class_id": 3, "box_caption": "other 0.001", "scores": {"class_score": 0.00115203857421875}, "domain": "pixel"}, {"position": {"minX": 427.0, "minY": 173.625, "maxX": 452.0, "maxY": 196.375}, "class_id": 3, "box_caption": "other 0.001", "scores": {"class_score": 0.0011463165283203125}, "domain": "pixel"}, {"position": {"minX": 404.75, "minY": 177.625, "maxX": 444.25, "maxY": 205.125}, "class_id": 1, "box_caption": "danger 0.001", "scores": {"class_score": 0.0011453628540039062}, "domain": "pixel"}, {"position": {"minX": 224.625, "minY": 263.75, "maxX": 233.875, "maxY": 276.25}, "class_id": 1, "box_caption": "danger 0.001", "scores": {"class_score": 0.0011167526245117188}, "domain": "pixel"}, {"position": {"minX": 195.5, "minY": 204.0, "maxX": 208.75, "maxY": 219.0}, "class_id": 2, "box_caption": "mandatory 0.001", "scores": {"class_score": 0.001068115234375}, "domain": "pixel"}, {"position": {"minX": 377.25, "minY": 299.0, "maxX": 414.25, "maxY": 329.5}, "class_id": 3, "box_caption": "other 0.001", "scores": {"class_score": 0.0010423660278320312}, "domain": "pixel"}, {"position": {"minX": 410.25, "minY": 165.25, "maxX": 446.75, "maxY": 196.5}, "class_id": 3, "box_caption": "other 0.001", "scores": {"class_score": 0.0010395050048828125}, "domain": "pixel"}, {"position": {"minX": 505.75, "minY": 103.25, "maxX": 541.0, "maxY": 130.125}, "class_id": 3, "box_caption": "other 0.001", "scores": {"class_score": 0.0010347366333007812}, "domain": "pixel"}, {"position": {"minX": 254.75, "minY": 238.25, "maxX": 266.75, "maxY": 252.0}, "class_id": 0, "box_caption": "prohibitory 0.001", "scores": {"class_score": 0.0010251998901367188}, "domain": "pixel"}, {"position": {"minX": 209.125, "minY": 248.0, "maxX": 237.625, "maxY": 280.0}, "class_id": 2, "box_caption": "mandatory 0.001", "scores": {"class_score": 0.0010166168212890625}, "domain": "pixel"}], "class_labels": {"0": "prohibitory", "1": "danger", "2": "mandatory", "3": "other"}}