{"box_data": [{"position": {"minX": 415.0, "minY": 205.5, "maxX": 431.5, "maxY": 221.75}, "class_id": 0, "box_caption": "prohibitory 0.899", "scores": {"class_score": 0.8994140625}, "domain": "pixel"}, {"position": {"minX": 411.25, "minY": 184.0, "maxX": 435.25, "maxY": 205.75}, "class_id": 1, "box_caption": "danger 0.849", "scores": {"class_score": 0.8486328125}, "domain": "pixel"}, {"position": {"minX": 437.75, "minY": 253.0, "maxX": 446.75, "maxY": 261.5}, "class_id": 0, "box_caption": "prohibitory 0.173", "scores": {"class_score": 0.1729736328125}, "domain": "pixel"}, {"position": {"minX": 412.0, "minY": 184.125, "maxX": 434.5, "maxY": 205.375}, "class_id": 0, "box_caption": "prohibitory 0.044", "scores": {"class_score": 0.043975830078125}, "domain": "pixel"}, {"position": {"minX": 412.25, "minY": 184.25, "maxX": 434.75, "maxY": 205.75}, "class_id": 2, "box_caption": "mandatory 0.034", "scores": {"class_score": 0.03424072265625}, "domain": "pixel"}, {"position": {"minX": 414.75, "minY": 196.25, "maxX": 432.25, "maxY": 213.5}, "class_id": 0, "box_caption": "prohibitory 0.027", "scores": {"class_score": 0.02703857421875}, "domain": "pixel"}, {"position": {"minX": 413.75, "minY": 197.75, "maxX": 432.75, "maxY": 213.0}, "class_id": 1, "box_caption": "danger 0.021", "scores": {"class_score": 0.0214080810546875}, "domain": "pixel"}, {"position": {"minX": 411.5, "minY": 183.625, "maxX": 435.5, "maxY": 205.625}, "class_id": 3, "box_caption": "other 0.021", "scores": {"class_score": 0.0211334228515625}, "domain": "pixel"}, {"position": {"minX": 414.25, "minY": 205.125, "maxX": 432.75, "maxY": 222.375}, "class_id": 2, "box_caption": "mandatory 0.019", "scores": {"class_score": 0.019073486328125}, "domain": "pixel"}, {"position": {"minX": 414.75, "minY": 204.625, "maxX": 431.75, "maxY": 222.625}, "class_id": 1, "box_caption": "danger 0.015", "scores": {"class_score": 0.01499176025390625}, "domain": "pixel"}, {"position": {"minX": 413.5, "minY": 201.0, "maxX": 436.0, "maxY": 226.75}, "class_id": 0, "box_caption": "prohibitory 0.013", "scores": {"class_score": 0.013458251953125}, "domain": "pixel"}, {"position": {"minX": 437.75, "minY": 253.0, "maxX": 446.75, "maxY": 261.5}, "class_id": 1, "box_caption": "danger 0.013", "scores": {"class_score": 0.01299285888671875}, "domain": "pixel"}, {"position": {"minX": 414.25, "minY": 205.125, "maxX": 432.75, "maxY": 222.375}, "class_id": 3, "box_caption": "other 0.012", "scores": {"class_score": 0.01204681396484375}, "domain": "pixel"}, {"position": {"minX": 437.75, "minY": 252.875, "maxX": 445.75, "maxY": 260.5}, "class_id": 3, "box_caption": "other 0.008", "scores": {"class_score": 0.00763702392578125}, "domain": "pixel"}, {"position": {"minX": 408.25, "minY": 176.5, "maxX": 434.75, "maxY": 201.5}, "class_id": 1, "box_caption": "danger 0.007", "scores": {"class_score": 0.006549835205078125}, "domain": "pixel"}, {"position": {"minX": 437.75, "minY": 253.0, "maxX": 446.75, "maxY": 261.5}, "class_id": 2, "box_caption": "mandatory 0.004", "scores": {"class_score": 0.0042877197265625}, "domain": "pixel"}, {"position": {"minX": 413.5, "minY": 190.5, "maxX": 432.5, "maxY": 211.5}, "class_id": 1, "box_caption": "danger 0.003", "scores": {"class_score": 0.0032711029052734375}, "domain": "pixel"}, {"position": {"minX": 197.125, "minY": 252.375, "maxX": 208.125, "maxY": 262.25}, "class_id": 1, "box_caption": "danger 0.003", "scores": {"class_score": 0.0032215118408203125}, "domain": "pixel"}, {"position": {"minX": 413.5, "minY": 201.0, "maxX": 436.0, "maxY": 226.75}, "class_id": 1, "box_caption": "danger 0.003", "scores": {"class_score": 0.0026264190673828125}, "domain": "pixel"}, {"position": {"minX": 413.5, "minY": 201.0, "maxX": 436.0, "maxY": 226.75}, "class_id": 2, "box_caption": "mandatory 0.002", "scores": {"class_score": 0.0024318695068359375}, "domain": "pixel"}, {"position": {"minX": 413.5, "minY": 201.0, "maxX": 436.0, "maxY": 226.75}, "class_id": 3, "box_caption": "other 0.002", "scores": {"class_score": 0.0022983551025390625}, "domain": "pixel"}, {"position": {"minX": 410.75, "minY": 198.25, "maxX": 431.25, "maxY": 231.75}, "class_id": 0, "box_caption": "prohibitory 0.002", "scores": {"class_score": 0.00211334228515625}, "domain": "pixel"}, {"position": {"minX": 404.5, "minY": 172.875, "maxX": 453.5, "maxY": 220.875}, "class_id": 1, "box_caption": "danger 0.002", "scores": {"class_score": 0.0019140243530273438}, "domain": "pixel"}, {"position": {"minX": 197.125, "minY": 252.375, "maxX": 208.125, "maxY": 262.25}, "class_id": 0, "box_caption": "prohibitory 0.002", "scores": {"class_score": 0.001865386962890625}, "domain": "pixel"}, {"position": {"minX": 215.75, "minY": 249.5, "maxX": 224.5, "maxY": 258.25}, "class_id": 0, "box_caption": "prohibitory 0.002", "scores": {"class_score": 0.0018320083618164062}, "domain": "pixel"}, {"position": {"minX": 410.0, "minY": 181.75, "maxX": 432.5, "maxY": 212.0}, "class_id": 2, "box_caption": "mandatory 0.001", "scores": {"class_score": 0.001434326171875}, "domain": "pixel"}, {"position": {"minX": 411.75, "minY": 179.75, "maxX": 439.75, "maxY": 208.75}, "class_id": 0, "box_caption": "prohibitory 0.001", "scores": {"class_score": 0.0013952255249023438}, "domain": "pixel"}, {"position": {"minX": 206.375, "minY": 267.25, "maxX": 214.125, "maxY": 274.25}, "class_id": 0, "box_caption": "prohibitory 0.001", "scores": {"class_score": 0.00131988525390625}, "domain": "pixel"}, {"position": {"minX": 421.5, "minY": 209.0, "maxX": 442.5, "maxY": 231.75}, "class_id": 0, "box_caption": "prohibitory 0.001", "scores": {"class_score": 0.0012350082397460938}, "domain": "pixel"}, {"position": {"minX": 414.75, "minY": 196.25, "maxX": 432.25, "maxY": 213.5}, "class_id": 2, "box_caption": "mandatory 0.001", "scores": {"class_score": 0.0010776519775390625}, "domain": "pixel"}], "class_labels": {"0": "prohibitory", "1": "danger", "2": "mandatory", "3": "other"}}